mpl_tune/__init__.py
mpl_tune/size.py
mpl_tune/text.py
mpl_tune-0.3.dist-info/LICENSE
mpl_tune-0.3.dist-info/METADATA
mpl_tune-0.3.dist-info/WHEEL
mpl_tune-0.3.dist-info/top_level.txt
mpl_tune-0.3.dist-info/RECORD
