Metadata-Version: 2.1
Name: mpl-tune
Version: 0.3
Summary: A collection of matplotlib tuning scripts
Home-page: https://github.com/aemsenhuber/mpl_tune
Author: Alexandre Emsenhuber
Author-email: emsenhuber@lpl.arizona.edu
License: UNKNOWN
Platform: UNKNOWN
Classifier: Programming Language :: Python :: 3
Classifier: License :: OSI Approved :: Apache Software License
Classifier: Operating System :: OS Independent
